oui.py
ouisearch-0.0.4.dist-info/LICENSE
ouisearch-0.0.4.dist-info/METADATA
ouisearch-0.0.4.dist-info/WHEEL
ouisearch-0.0.4.dist-info/top_level.txt
ouisearch-0.0.4.dist-info/RECORD
