Metadata-Version: 2.1
Name: ouisearch
Version: 0.0.4
Summary: Module and command line tool for search the IEEE OUI code databases
Home-page: https://github.com/ejohnfel/ouisearch
Author: Eric Johnfelt
Author-email: ejohnfel@hotmail.com
License: UNKNOWN
Project-URL: Bug Tracker, https://github.com/ejohnfel/ouisearch/issues
Platform: UNKNOWN
Classifier: Programming Language :: Python :: 3
Classifier: License :: OSI Approved :: MIT License
Classifier: Operating System :: OS Independent
Requires-Python: >=3.0
License-File: LICENSE
Requires-Dist: py-helper-mod
